brainlib/__init__.py
brainlib-0.0.1.post20241228.dist-info/METADATA
brainlib-0.0.1.post20241228.dist-info/WHEEL
brainlib-0.0.1.post20241228.dist-info/top_level.txt
brainlib-0.0.1.post20241228.dist-info/RECORD
